{
    "products": [
        {
            "id": 1,
            "title": "تصميم موقع ويب احترافي",
            "description": "تصميم موقع ويب متجاوب وعصري باستخدام أحدث التقنيات. يشمل تصميم جميع الصفحات الأساسية مع تحسين السيو وسرعة التحميل.",
            "price": 500,
            "category": "programming",
            "image": "https://images.unsplash.com/photo-1547658719-da2b51169166?w=600&h=400&fit=crop",
            "sellerId": "user_demo_seller",
            "sellerName": "بائع تجريبي",
            "rating": 4.8,
            "reviews": 12,
            "createdAt": 1702400000000,
            "status": "active"
        },
        {
            "id": 2,
            "title": "تصميم شعار وهوية بصرية",
            "description": "تصميم شعار فريد مع ملفات قابلة للتعديل وهوية بصرية كاملة تشمل الألوان والخطوط وتطبيقات الشعار.",
            "price": 300,
            "category": "design",
            "image": "https://images.unsplash.com/photo-1626785774573-4b799315345d?w=600&h=400&fit=crop",
            "sellerId": "user_demo_seller",
            "sellerName": "بائع تجريبي",
            "rating": 4.9,
            "reviews": 25,
            "createdAt": 1702400100000,
            "status": "active"
        },
        {
            "id": 3,
            "title": "لوحة فنية مرسومة يدوياً",
            "description": "لوحة فنية أصلية مرسومة بالألوان الزيتية على قماش حقيقي. قطعة فنية فريدة لتزيين منزلك أو مكتبك.",
            "price": 450,
            "category": "art",
            "image": "https://images.unsplash.com/photo-1579783902614-a3fb3927b6a5?w=600&h=400&fit=crop",
            "sellerId": "user_demo_student",
            "sellerName": "طالب تجريبي",
            "rating": 5.0,
            "reviews": 8,
            "createdAt": 1702400200000,
            "status": "active"
        },
        {
            "id": 4,
            "title": "إكسسوارات يدوية مميزة",
            "description": "مجموعة من الإكسسوارات المصنوعة يدوياً بتصاميم فريدة. تشمل أساور، قلادات، وأقراط بألوان متنوعة.",
            "price": 150,
            "category": "crafts",
            "image": "https://images.unsplash.com/photo-1611085583191-a3b181a88401?w=600&h=400&fit=crop",
            "sellerId": "user_demo_student",
            "sellerName": "طالب تجريبي",
            "rating": 4.7,
            "reviews": 15,
            "createdAt": 1702400300000,
            "status": "active"
        },
        {
            "id": 5,
            "title": "دروس خصوصية في البرمجة",
            "description": "دروس أونلاين في أساسيات البرمجة وتطوير المواقع للمبتدئين. تشمل HTML, CSS, JavaScript مع مشاريع عملية.",
            "price": 100,
            "category": "education",
            "image": "https://images.unsplash.com/photo-1587620962725-abab7fe55159?w=600&h=400&fit=crop",
            "sellerId": "user_demo_seller",
            "sellerName": "بائع تجريبي",
            "rating": 4.6,
            "reviews": 30,
            "createdAt": 1702400400000,
            "status": "active"
        },
        {
            "id": 6,
            "title": "تطبيق موبايل متكامل",
            "description": "تطوير تطبيق موبايل لنظامي Android و iOS بتصميم احترافي. يشمل لوحة تحكم وقاعدة بيانات.",
            "price": 800,
            "category": "programming",
            "image": "https://images.unsplash.com/photo-1512941937669-90a1b58e7e9c?w=600&h=400&fit=crop",
            "sellerId": "user_demo_seller",
            "sellerName": "بائع تجريبي",
            "rating": 4.9,
            "reviews": 18,
            "createdAt": 1702400500000,
            "status": "active"
        },
        {
            "id": 7,
            "title": "تصميم بوستر إعلاني",
            "description": "تصميم بوستر إعلاني جذاب لوسائل التواصل الاجتماعي. يشمل نسخ متعددة لمختلف المنصات.",
            "price": 80,
            "category": "design",
            "image": "https://images.unsplash.com/photo-1561070791-2526d30994b5?w=600&h=400&fit=crop",
            "sellerId": "user_demo_student",
            "sellerName": "طالب تجريبي",
            "rating": 4.8,
            "reviews": 40,
            "createdAt": 1702400600000,
            "status": "active"
        },
        {
            "id": 8,
            "title": "مونتاج فيديوهات احترافي",
            "description": "مونتاج فيديوهات بجودة عالية مع مؤثرات بصرية وصوتية مميزة. مناسب لليوتيوب والإنستجرام.",
            "price": 200,
            "category": "other",
            "image": "https://images.unsplash.com/photo-1574717024653-61fd2cf4d44d?w=600&h=400&fit=crop",
            "sellerId": "user_demo_seller",
            "sellerName": "بائع تجريبي",
            "rating": 4.7,
            "reviews": 22,
            "createdAt": 1702400700000,
            "status": "active"
        }
    ],
    "nextId": 9
}